{"info":{"_postman_id":"aefd10e8-20c2-40e1-bf06-3d3c44ffa836","name":"sda","schema":"https://schema.getpostman.com/json/collection/v2.1.0/collection.json"},"item":[{"name":"Sample endpoint: Returns details about a particular user","id":"70e4d156-0468-4a0c-bc99-a7c58c6516a6","request":{"method":"GET","header":[],"url":{"raw":"{{baseUrl}}/user?id=-93476678","host":["{{baseUrl}}"],"path":["user"],"query":[{"key":"id","value":"-93476678","description":"(Required) ID of the user"}]}},"response":[{"id":"730a21b4-2bf7-448f-aa00-9abdda956efe","name":"Sample response: Details about a user by ID","originalRequest":{"method":"GET","header":[],"url":{"raw":"{{baseUrl}}/user?id=-93476678","host":["{{baseUrl}}"],"path":["user"],"query":[{"key":"id","value":"-93476678"}]}},"status":"OK","code":200,"_postman_previewlanguage":"json","header":[{"disabled":false,"description":"A link to the next page of responses","key":"x-next","value":"cupidatat"},{"key":"Content-Type","value":"application/json"}],"cookie":[],"responseTime":null,"body":"{\n \"id\": -3873867,\n \"name\": \"aliquip veniam mollit\",\n \"tag\": \"nostrud elit labore Ex\"\n}"},{"id":"a2290d43-b802-4ff8-82c5-6d657ad72eaa","name":"Unexpected error","originalRequest":{"method":"GET","header":[],"url":{"raw":"{{baseUrl}}/user?id=-93476678","host":["{{baseUrl}}"],"path":["user"],"query":[{"key":"id","value":"-93476678"}]}},"status":"Internal Server Error","code":500,"_postman_previewlanguage":"json","header":[{"key":"Content-Type","value":"application/json"}],"cookie":[],"responseTime":null,"body":"{\n \"code\": -30866979,\n \"message\": \"dolore nisi ullamco proident\"\n}"}]}],"variable":[{"id":"8e7582b5-7466-4784-b2c6-a327deb969ba","key":"baseUrl","value":"http://localhost:3000","type":"string"}]}